valhallabot2/__init__.py
valhallabot2/core.py
valhallabot2-0.1.0.dist-info/licenses/LICENSE
valhallabot2-0.1.0.dist-info/METADATA
valhallabot2-0.1.0.dist-info/WHEEL
valhallabot2-0.1.0.dist-info/top_level.txt
valhallabot2-0.1.0.dist-info/RECORD
