Metadata-Version: 2.4
Name: valhallabot2
Version: 0.1.0
Summary: مكتبة بايثون لإرسال ملفات من مجلد معين عبر بوت تليجرام
Author: valhalla
Classifier: Programming Language :: Python :: 3
Classifier: Operating System :: OS Independent
Requires-Python: >=3.6
License-File: LICENSE
Requires-Dist: pyTelegramBotAPI
Dynamic: author
Dynamic: classifier
Dynamic: description
Dynamic: license-file
Dynamic: requires-dist
Dynamic: requires-python
Dynamic: summary
